{
    "version": "2.1.2",
    "architecture": {
        "32bit": {
            "url": "https://github.com/lucagrulla/cw/releases/download/v2.1.2/cw_2.1.2_Windows_i386.tar.gz",
            "bin": "cw.exe",
            "hash": "0f4e1830a3a4f9ef75e6860037c0ce0b5609e31947456834e48f8e8e8cc58897"
        },
        "64bit": {
            "url": "https://github.com/lucagrulla/cw/releases/download/v2.1.2/cw_2.1.2_Windows_x86_64.tar.gz",
            "bin": "cw.exe",
            "hash": "e3fd0d66d2140aec51d5dc23bd52b662fe4313df8d6668788c987d3d8e01b243"
        }
    },
    "homepage": "https://www.lucagrulla.com/cw",
    "license": "Apache-2.0",
    "description": "The best way to tail AWS Cloudwatch Logs from your terminal",
    "persist": [
        "data",
        "config.toml"
    ]
}